Workbook

Sheet Notes
A1: Indian FMCG Financial Statement & Ratio Analysis (FY21–FY26)
A3: Purpose
A4: Compare the financial performance of 5 listed Indian FMCG companies over 5 years using ratio and DuPont analysis.
A6: Companies
A7: HUL: Hindustan Unilever Ltd
A8: ITC: ITC Ltd
A9: Dabur: Dabur India Ltd
A10: Britannia: Britannia Industries Ltd
A11: Marico: Marico Ltd
A13: Data source
A14: Consolidated annual financials from Screener.in (compiled from company filings), retrieved 26 Sep 2026. Figures in ₹ crore. Fiscal years end 31 March (FY26 = Apr 2025–Mar 2026).
A15: HUL: https://www.screener.in/company/HINDUNILVR/consolidated/
... A43: Educational portfolio project. Not investment advice.

Sheet Financials
A1: Financial Statements (₹ crore, consolidated)
A2: Source: Screener.in consolidated annual data, retrieved 26 Sep 2026. See Notes sheet for links.
A4: HUL | B4: Line Item | D4: FY21 | E4: FY22 | F4: FY23 | G4: FY24 | H4: FY25 | I4: FY26
A5: HUL | B5: Income Statement
A6: HUL | B6: Sales | D6: 47028 | E6: 52446 | F6: 60580 | G6: 61896 | H6: 61328 | I6: 64468
A7: HUL | B7: Expenses | D7: 35402 | E7: 39589 | F7: 46433 | G7: 47237 | H7: 46630 | I7: 49429
A8: HUL | B8: Operating Profit (EBITDA) | D8: 11626 | E8: 12857 | F8: 14147 | G8: 14659 | H8: 14698 | I8: 15039
A9: HUL | B9: Other Income | D9: 170 | E9: 219 | F9: 448 | G9: 817 | H9: 1355 | I9: 4923
A10: HUL | B10: Interest | D10: 117 | E10: 106 | F10: 114 | G10: 334 | H10: 381 | I10: 410
A11: HUL | B11: Depreciation | D11: 1074 | E11: 1091 | F11: 1137 | G11: 1216 | H11: 1253 | I11: 1333
A12: HUL | B12: Profit Before Tax | D12: 10605 | E12: 11879 | F12: 13344 | G12: 13926 | H12: 14419 | I12: 18219
A13: HUL | B13: Net Profit | D13: 7999 | E13: 8892 | F13: 10143 | G13: 10282 | H13: 10671 | I13: 15059
A14: HUL | B14: EPS (₹) | D14: 34.03 | E14: 37.79 | F14: 43.07 | G14: 43.74 | H14: 45.32 | I14: 64.01
A15: HUL | B15: Dividend Payout % | D15: 1.19 | E15: 0.9 | F15: 0.91 | G15: 0.96 | H15: 1.17 | I15: 0.64
A16: HUL | B16: Balance Sheet
A17: HUL | B17: Equity Capital | D17: 235 | E17: 235 | F17: 235 | G17: 235 | H17: 235 | I17: 235
A18: HUL | B18: Reserves | D18: 47439 | E18: 48826 | F18: 50069 | G18: 50983 | H18: 49167 | I18: 48504
A19: HUL | B19: Borrowings | D19: 0 | E19: 1043 | F19: 1219 | G19: 1484 | H19: 1648 | I19: 1478
A20: HUL | B20: Other Liabilities | D20: 21066 | E20: 20402 | F20: 21554 | G20: 25787 | H20: 28813 | I20: 29521
A21: HUL | B21: Total Liabilities | D21: 68740 | E21: 70506 | F21: 73077 | G21: 78489 | H21: 79863 | I21: 79738
A22: HUL | B22: Fixed Assets (incl. goodwill) | D22: 51443 | E22: 51473 | F22: 52678 | G22: 53744 | H22: 54335 | I22: 57428
A23: HUL | B23: Capital Work in Progress | D23: 745 | E23: 1313 | F23: 1132 | G23: 1025 | H23: 1009 | I23: 880
A24: HUL | B24: Investments | D24: 2709 | E24: 3521 | F24: 2882 | G24: 4625 | H24: 3810 | I24: 4359
A25: HUL | B25: Other Assets | D25: 13843 | E25: 14199 | F25: 16385 | G25: 19095 | H25: 20709 | I25: 17071
A26: HUL | B26: Total Assets | D26: =D22+D23+D24+D25 -> 68740 | E26: =E22+E23+E24+E25 -> 70506 | F26: =F22+F23+F24+F25 -> 73077 | G26: =G22+G23+G24+G25 -> 78489 | H26: =H22+H23+H24+H25 -> 79863 | I26: =I22+I23+I24+I25 -> 79738
A27: HUL | B27: Cash Flow
A28: HUL | B28: Cash from Operations (CFO) | D28: 9163 | E28: 9048 | F28: 9991 | G28: 15469 | H28: 11886 | I28: 10999
A29: HUL | B29: Cash from Investing | D29: -1228 | E29: -1728 | F29: -1484 | G29: -5324 | H29: 6473 | I29: -3676
A30: HUL | B30: Cash from Financing | D30: -9309 | E30: -8015 | F30: -8953 | G30: -10034 | H30: -13101 | I30: -10810
A31: HUL | B31: Free Cash Flow | D31: 5097 | E31: 7995 | F31: 8980 | G31: 14012 | H31: 10624 | I31: 9667
A32: HUL | B32: Working Capital Days (reported)
A33: HUL | B33: Debtor Days | D33: 14 | E33: 16 | F33: 19 | G33: 18 | H33: 23 | I33: 19
A34: HUL | B34: Inventory Days | D34: 66 | E34: 65 | F34: 55 | G34: 55 | H34: 61 | I34: 61
A35: HUL | B35: Days Payable | D35: 163 | E35: 145 | F35: 123 | G35: 143 | H35: 156 | I35: 169
A36: HUL | B36: Derived (formulas)
A37: HUL | B37: Shareholders' Equity | D37: =D17+D18 -> 47674 | E37: =E17+E18 -> 49061 | F37: =F17+F18 -> 50304 | G37: =G17+G18 -> 51218 | H37: =H17+H18 -> 49402 | I37: =I17+I18 -> 48739
A38: HUL | B38: EBIT (PBT + Interest) | D38: =D12+D10 -> 10722 | E38: =E12+E10 -> 11985 | F38: =F12+F10 -> 13458 | G38: =G12+G10 -> 14260 | H38: =H12+H10 -> 14800 | I38: =I12+I10 -> 18629
A39: HUL | B39: Capital Employed (Equity + Borrowings) | D39: =D37+D19 -> 47674 | E39: =E37+E19 -> 50104 | F39: =F37+F19 -> 51523 | G39: =G37+G19 -> 52702 | H39: =H37+H19 -> 51050 | I39: =I37+I19 -> 50217
A40: HUL | B40: Balance Check (Assets − Liabilities) | D40: =D26-D21 -> 0 | E40: =E26-E21 -> 0 | F40: =F26-F21 -> 0 | G40: =G26-G21 -> 0 | H40: =H26-H21 -> 0 | I40: =I26-I21 -> 0
A42: ITC | B42: Line Item | D42: FY21 | E42: FY22 | F42: FY23 | G42: FY24 | H42: FY25 | I42: FY26
A43: ITC | B43: Income Statement
A44: ITC | B44: Sales | D44: 49257 | E44: 60645 | F44: 70919 | G44: 67932 | H44: 75323 | I44: 78868
A45: ITC | B45: Expenses | D45: 32193 | E45: 40021 | F45: 45215 | G45: 42744 | H45: 49492 | I45: 51562
A46: ITC | B46: Operating Profit (EBITDA) | D46: 17065 | E46: 20623 | F46: 25704 | G46: 25188 | H46: 25832 | I46: 27306
A47: ITC | B47: Other Income | D47: 2577 | E47: 1910 | F47: 2098 | G47: 3330 | H47: 17803 | I47: 2523
A48: ITC | B48: Interest | D48: 58 | E48: 60 | F48: 78 | G48: 39 | H48: 45 | I48: 85
A49: ITC | B49: Depreciation | D49: 1646 | E49: 1732 | F49: 1809 | G49: 1518 | H49: 1646 | I49: 1711
A50: ITC | B50: Profit Before Tax | D50: 17938 | E50: 20740 | F50: 25915 | G50: 26961 | H50: 41943 | I50: 28033
A51: ITC | B51: Net Profit | D51: 13383 | E51: 15503 | F51: 19477 | G51: 20751 | H51: 35052 | I51: 21018
A52: ITC | B52: EPS (₹) | D52: 10.69 | E52: 12.37 | F52: 15.44 | G52: 16.39 | H52: 27.77 | I52: 16.51
A53: ITC | B53: Dividend Payout % | D53: 1.01 | E53: 0.93 | F53: 1 | G53: 0.84 | H53: 0.52 | I53: 0.88
A54: ITC | B54: Balance Sheet
A55: ITC | B55: Equity Capital | D55: 1231 | E55: 1232 | F55: 1243 | G55: 1248 | H55: 1251 | I55: 1253
A56: ITC | B56: Reserves | D56: 59116 | E56: 61223 | F56: 67912 | G56: 73259 | H56: 68779 | I56: 71254
A57: ITC | B57: Borrowings | D57: 271 | E57: 249 | F57: 306 | G57: 303 | H57: 285 | I57: 2399
A58: ITC | B58: Other Liabilities | D58: 13143 | E58: 14491 | F58: 16370 | G58: 16944 | H58: 17688 | I58: 18731
A59: ITC | B59: Total Liabilities | D59: 73761 | E59: 77196 | F59: 85831 | G59: 91754 | H59: 88003 | I59: 93637
A60: ITC | B60: Fixed Assets (incl. goodwill) | D60: 23298 | E60: 24232 | F60: 25851 | G60: 27820 | H60: 21955 | I60: 22443
A61: ITC | B61: Capital Work in Progress | D61: 4011 | E61: 3226 | F61: 3003 | G61: 2861 | H61: 1091 | I61: 1602
A62: ITC | B62: Investments | D62: 24871 | E62: 24841 | F62: 29415 | G62: 31114 | H62: 34720 | I62: 38128
A63: ITC | B63: Other Assets | D63: 21580 | E63: 24898 | F63: 27561 | G63: 29959 | H63: 30237 | I63: 31464
A64: ITC | B64: Total Assets | D64: =D60+D61+D62+D63 -> 73760 | E64: =E60+E61+E62+E63 -> 77197 | F64: =F60+F61+F62+F63 -> 85830 | G64: =G60+G61+G62+G63 -> 91754 | H64: =H60+H61+H62+H63 -> 88003 | I64: =I60+I61+I62+I63 -> 93637
A65: ITC | B65: Cash Flow
A66: ITC | B66: Cash from Operations (CFO) | D66: 12527 | E66: 15776 | F66: 18878 | G66: 17179 | H66: 17627 | I66: 18464
A67: ITC | B67: Cash from Investing | D67: 5740 | E67: -2238 | F67: -5732 | G67: 1563 | H67: -564 | I67: -2321
A68: ITC | B68: Cash from Financing | D68: -18634 | E68: -13580 | F68: -13006 | G68: -18551 | H68: -17037 | I68: -16147
A69: ITC | B69: Free Cash Flow | D69: 10693 | E69: 13767 | F69: 16184 | G69: 13724 | H69: 15524 | I69: 16332
A70: ITC | B70: Working Capital Days (reported)
A71: ITC | B71: Debtor Days | D71: 19 | E71: 15 | F71: 15 | G71: 22 | H71: 23 | I71: 18
A72: ITC | B72: Inventory Days | D72: 189 | E72: 150 | F72: 148 | G72: 191 | H72: 178 | I72: 209
A73: ITC | B73: Days Payable | D73: 78 | E73: 61 | F73: 59 | G73: 65 | H73: 55 | I73: 63
A74: ITC | B74: Derived (formulas)
A75: ITC | B75: Shareholders' Equity | D75: =D55+D56 -> 60347 | E75: =E55+E56 -> 62455 | F75: =F55+F56 -> 69155 | G75: =G55+G56 -> 74507 | H75: =H55+H56 -> 70030 | I75: =I55+I56 -> 72507
A76: ITC | B76: EBIT (PBT + Interest) | D76: =D50+D48 -> 17996 | E76: =E50+E48 -> 20800 | F76: =F50+F48 -> 25993 | G76: =G50+G48 -> 27000 | H76: =H50+H48 -> 41988 | I76: =I50+I48 -> 28118
A77: ITC | B77: Capital Employed (Equity + Borrowings) | D77: =D75+D57 -> 60618 | E77: =E75+E57 -> 62704 | F77: =F75+F57 -> 69461 | G77: =G75+G57 -> 74810 | H77: =H75+H57 -> 70315 | I77: =I75+I57 -> 74906
A78: ITC | B78: Balance Check (Assets − Liabilities) | D78: =D64-D59 -> -1 | E78: =E64-E59 -> 1 | F78: =F64-F59 -> -1 | G78: =G64-G59 -> 0 | H78: =H64-H59 -> 0 | I78: =I64-I59 -> 0
A80: Dabur | B80: Line Item | D80: FY21 | E80: FY22 | F80: FY23 | G80: FY24 | H80: FY25 | I80: FY26
A81: Dabur | B81: Income Statement
A82: Dabur | B82: Sales | D82: 9562 | E82: 10889 | F82: 11530 | G82: 12404 | H82: 12563 | I82: 13193
A83: Dabur | B83: Expenses | D83: 7560 | E83: 8637 | F83: 9367 | G83: 10004 | H83: 10247 | I83: 10743
A84: Dabur | B84: Operating Profit (EBITDA) | D84: 2002 | E84: 2252 | F84: 2162 | G84: 2400 | H84: 2316 | I84: 2450
A85: Dabur | B85: Other Income | D85: 325 | E85: 308 | F85: 445 | G85: 482 | H85: 551 | I85: 585
A86: Dabur | B86: Interest | D86: 31 | E86: 39 | F86: 78 | G86: 124 | H86: 164 | I86: 145
A87: Dabur | B87: Depreciation | D87: 240 | E87: 253 | F87: 311 | G87: 399 | H87: 446 | I87: 469
A88: Dabur | B88: Profit Before Tax | D88: 2056 | E88: 2269 | F88: 2219 | G88: 2359 | H88: 2258 | I88: 2420
A89: Dabur | B89: Net Profit | D89: 1695 | E89: 1742 | F89: 1701 | G89: 1811 | H89: 1740 | I89: 1869
A90: Dabur | B90: EPS (₹) | D90: 9.58 | E90: 9.84 | F90: 9.64 | G90: 10.4 | H90: 9.97 | I90: 10.68
A91: Dabur | B91: Dividend Payout % | D91: 0.5 | E91: 0.53 | F91: 0.54 | G91: 0.53 | H91: 0.8 | I91: 0.77
A92: Dabur | B92: Balance Sheet
A93: Dabur | B93: Equity Capital | D93: 177 | E93: 177 | F93: 177 | G93: 177 | H93: 177 | I93: 177
A94: Dabur | B94: Reserves | D94: 7487 | E94: 8205 | F94: 8796 | G94: 9689 | H94: 10623 | I94: 11242
A95: Dabur | B95: Borrowings | D95: 509 | E95: 1030 | F95: 1174 | G95: 1365 | H95: 950 | I95: 1287
A96: Dabur | B96: Other Liabilities | D96: 2661 | E96: 2872 | F96: 3505 | G96: 3885 | H96: 4479 | I96: 4773
A97: Dabur | B97: Total Liabilities | D97: 10833 | E97: 12284 | F97: 13652 | G97: 15116 | H97: 16230 | I97: 17480
A98: Dabur | B98: Fixed Assets (incl. goodwill) | D98: 2243 | E98: 2308 | F98: 3579 | G98: 3815 | H98: 3990 | I98: 3938
A99: Dabur | B99: Capital Work in Progress | D99: 147 | E99: 168 | F99: 175 | G99: 232 | H99: 169 | I99: 139
A100: Dabur | B100: Investments | D100: 4160 | E100: 6220 | F100: 6265 | G100: 6933 | H100: 7468 | I100: 8947
A101: Dabur | B101: Other Assets | D101: 4283 | E101: 3589 | F101: 3633 | G101: 4136 | H101: 4603 | I101: 4456
A102: Dabur | B102: Total Assets | D102: =D98+D99+D100+D101 -> 10833 | E102: =E98+E99+E100+E101 -> 12285 | F102: =F98+F99+F100+F101 -> 13652 | G102: =G98+G99+G100+G101 -> 15116 | H102: =H98+H99+H100+H101 -> 16230 | I102: =I98+I99+I100+I101 -> 17480
A103: Dabur | B103: Cash Flow
...

Sheet Ratios
A1: Ratio Analysis
A2: All values are formulas linked to the Financials sheet. Averages use opening and closing balances.
A4: HUL | B4: Ratio | C4: Formula | D4: FY21 | E4: FY22 | F4: FY23 | G4: FY24 | H4: FY25 | I4: FY26 | J4: 5Y Avg (FY22–26)
A5: HUL | B5: Growth
A6: HUL | B6: Revenue Growth (YoY) | C6: Sales / previous year Sales − 1 | D6: n/a | E6: =Financials!E6/Financials!D6-1 -> 0.11520796 | F6: =Financials!F6/Financials!E6-1 -> 0.15509286 | G6: =Financials!G6/Financials!F6-1 -> 0.021723341 | H6: =Financials!H6/Financials!G6-1 -> -0.0091766835 | I6: =Financials!I6/Financials!H6-1 -> 0.051200104 | J6: =AVERAGE(E6:I6) -> 0.066809516
A7: HUL | B7: Net Profit Growth (YoY) | C7: Net Profit / previous year Net Profit − 1 | D7: n/a | E7: =Financials!E13/Financials!D13-1 -> 0.11163895 | F7: =Financials!F13/Financials!E13-1 -> 0.14068826 | G7: =Financials!G13/Financials!F13-1 -> 0.013704032 | H7: =Financials!H13/Financials!G13-1 -> 0.037833106 | I7: =Financials!I13/Financials!H13-1 -> 0.41120795 | J7: =AVERAGE(E7:I7) -> 0.14301446
A8: HUL | B8: Profitability
A9: HUL | B9: Operating Margin (OPM) | C9: Operating Profit / Sales | D9: =Financials!D8/Financials!D6 -> 0.24721443 | E9: =Financials!E8/Financials!E6 -> 0.24514739 | F9: =Financials!F8/Financials!F6 -> 0.23352592 | G9: =Financials!G8/Financials!G6 -> 0.23683275 | H9: =Financials!H8/Financials!H6 -> 0.23966214 | I9: =Financials!I8/Financials!I6 -> 0.23327853 | J9: =AVERAGE(E9:I9) -> 0.23768935
A10: HUL | B10: Net Profit Margin | C10: Net Profit / Sales | D10: =Financials!D13/Financials!D6 -> 0.17009016 | E10: =Financials!E13/Financials!E6 -> 0.16954582 | F10: =Financials!F13/Financials!F6 -> 0.1674315 | G10: =Financials!G13/Financials!G6 -> 0.16611736 | H10: =Financials!H13/Financials!H6 -> 0.17399883 | I10: =Financials!I13/Financials!I6 -> 0.23358876 | J10: =AVERAGE(E10:I10) -> 0.18213645
A11: HUL | B11: Return on Equity (ROE) | C11: Net Profit / Average Shareholders' Equity | D11: n/a | E11: =Financials!E13/((Financials!E37+Financials!D37)/2) -> 0.18384246 | F11: =Financials!F13/((Financials!F37+Financials!E37)/2) -> 0.20415639 | G11: =Financials!G13/((Financials!G37+Financials!F37)/2) -> 0.20255708 | H11: =Financials!H13/((Financials!H37+Financials!G37)/2) -> 0.21210495 | I11: =Financials!I13/((Financials!I37+Financials!H37)/2) -> 0.30688499 | J11: =AVERAGE(E11:I11) -> 0.22190917
A12: HUL | B12: Return on Capital Employed (ROCE) | C12: EBIT / Average Capital Employed | D12: n/a | E12: =Financials!E38/((Financials!E39+Financials!D39)/2) -> 0.24514717 | F12: =Financials!F38/((Financials!F39+Financials!E39)/2) -> 0.26485088 | G12: =Financials!G38/((Financials!G39+Financials!F39)/2) -> 0.27363876 | H12: =Financials!H38/((Financials!H39+Financials!G39)/2) -> 0.28529571 | I12: =Financials!I38/((Financials!I39+Financials!H39)/2) -> 0.36791847 | J12: =AVERAGE(E12:I12) -> 0.2873702
A13: HUL | B13: Return on Assets (ROA) | C13: Net Profit / Average Total Assets | D13: n/a | E13: =Financials!E13/((Financials!E26+Financials!D26)/2) -> 0.12771642 | F13: =Financials!F13/((Financials!F26+Financials!E26)/2) -> 0.14128414 | G13: =Financials!G13/((Financials!G26+Financials!F26)/2) -> 0.13567687 | H13: =Financials!H13/((Financials!H26+Financials!G26)/2) -> 0.13477569 | I13: =Financials!I13/((Financials!I26+Financials!H26)/2) -> 0.18870809 | J13: =AVERAGE(E13:I13) -> 0.14563224
A14: HUL | B14: Efficiency
A15: HUL | B15: Asset Turnover | C15: Sales / Average Total Assets | D15: n/a | E15: =Financials!E6/((Financials!E26+Financials!D26)/2) -> 0.75328555 | F15: =Financials!F6/((Financials!F26+Financials!E26)/2) -> 0.84383249 | G15: =Financials!G6/((Financials!G26+Financials!F26)/2) -> 0.8167531 | H15: =Financials!H6/((Financials!H26+Financials!G26)/2) -> 0.77457815 | I15: =Financials!I6/((Financials!I26+Financials!H26)/2) -> 0.80786461 | J15: =AVERAGE(E15:I15) -> 0.79926278
A16: HUL | B16: Debtor Days | C16: As reported | D16: =Financials!D33 -> 14 | E16: =Financials!E33 -> 16 | F16: =Financials!F33 -> 19 | G16: =Financials!G33 -> 18 | H16: =Financials!H33 -> 23 | I16: =Financials!I33 -> 19 | J16: =AVERAGE(E16:I16) -> 19
A17: HUL | B17: Inventory Days | C17: As reported | D17: =Financials!D34 -> 66 | E17: =Financials!E34 -> 65 | F17: =Financials!F34 -> 55 | G17: =Financials!G34 -> 55 | H17: =Financials!H34 -> 61 | I17: =Financials!I34 -> 61 | J17: =AVERAGE(E17:I17) -> 59.4
A18: HUL | B18: Payable Days | C18: As reported | D18: =Financials!D35 -> 163 | E18: =Financials!E35 -> 145 | F18: =Financials!F35 -> 123 | G18: =Financials!G35 -> 143 | H18: =Financials!H35 -> 156 | I18: =Financials!I35 -> 169 | J18: =AVERAGE(E18:I18) -> 147.2
A19: HUL | B19: Cash Conversion Cycle (days) | C19: Debtor Days + Inventory Days − Payable Days | D19: =D16+D17-D18 -> -83 | E19: =E16+E17-E18 -> -64 | F19: =F16+F17-F18 -> -49 | G19: =G16+G17-G18 -> -70 | H19: =H16+H17-H18 -> -72 | I19: =I16+I17-I18 -> -89 | J19: =AVERAGE(E19:I19) -> -68.8
A20: HUL | B20: Leverage & Coverage
A21: HUL | B21: Debt / Equity | C21: Borrowings / Shareholders' Equity (year-end) | D21: =Financials!D19/Financials!D37 -> 0 | E21: =Financials!E19/Financials!E37 -> 0.021259249 | F21: =Financials!F19/Financials!F37 -> 0.024232665 | G21: =Financials!G19/Financials!G37 -> 0.028974189 | H21: =Financials!H19/Financials!H37 -> 0.033358973 | I21: =Financials!I19/Financials!I37 -> 0.030324791 | J21: =AVERAGE(E21:I21) -> 0.027629973
A22: HUL | B22: Interest Coverage | C22: EBIT / Interest | D22: =IFERROR(Financials!D38/Financials!D10,0) -> 91.641026 | E22: =IFERROR(Financials!E38/Financials!E10,0) -> 113.06604 | F22: =IFERROR(Financials!F38/Financials!F10,0) -> 118.05263 | G22: =IFERROR(Financials!G38/Financials!G10,0) -> 42.694611 | H22: =IFERROR(Financials!H38/Financials!H10,0) -> 38.845144 | I22: =IFERROR(Financials!I38/Financials!I10,0) -> 45.436585 | J22: =AVERAGE(E22:I22) -> 71.619002
A23: HUL | B23: Cash Flow & Payout
A24: HUL | B24: CFO / Net Profit (earnings quality) | C24: Cash from Operations / Net Profit | D24: =Financials!D28/Financials!D13 -> 1.1455182 | E24: =Financials!E28/Financials!E13 -> 1.0175439 | F24: =Financials!F28/Financials!F13 -> 0.9850143 | G24: =Financials!G28/Financials!G13 -> 1.5044738 | H24: =Financials!H28/Financials!H13 -> 1.11386 | I24: =Financials!I28/Financials!I13 -> 0.73039378 | J24: =AVERAGE(E24:I24) -> 1.0702572
A25: HUL | B25: Free Cash Flow Margin | C25: Free Cash Flow / Sales | D25: =Financials!D31/Financials!D6 -> 0.10838224 | E25: =Financials!E31/Financials!E6 -> 0.15244251 | F25: =Financials!F31/Financials!F6 -> 0.14823374 | G25: =Financials!G31/Financials!G6 -> 0.22637973 | H25: =Financials!H31/Financials!H6 -> 0.17323245 | I25: =Financials!I31/Financials!I6 -> 0.14995036 | J25: =AVERAGE(E25:I25) -> 0.17004776
A26: HUL | B26: Dividend Payout | C26: As reported | D26: =Financials!D15 -> 1.19 | E26: =Financials!E15 -> 0.9 | F26: =Financials!F15 -> 0.91 | G26: =Financials!G15 -> 0.96 | H26: =Financials!H15 -> 1.17 | I26: =Financials!I15 -> 0.64 | J26: =AVERAGE(E26:I26) -> 0.916
A27: HUL | B27: DuPont Analysis of ROE
A28: HUL | B28: Net Profit Margin | C28: Net Profit / Sales | D28: =Financials!D13/Financials!D6 -> 0.17009016 | E28: =Financials!E13/Financials!E6 -> 0.16954582 | F28: =Financials!F13/Financials!F6 -> 0.1674315 | G28: =Financials!G13/Financials!G6 -> 0.16611736 | H28: =Financials!H13/Financials!H6 -> 0.17399883 | I28: =Financials!I13/Financials!I6 -> 0.23358876 | J28: =AVERAGE(E28:I28) -> 0.18213645
A29: HUL | B29: × Asset Turnover | C29: Sales / Average Total Assets | D29: n/a | E29: =Financials!E6/((Financials!E26+Financials!D26)/2) -> 0.75328555 | F29: =Financials!F6/((Financials!F26+Financials!E26)/2) -> 0.84383249 | G29: =Financials!G6/((Financials!G26+Financials!F26)/2) -> 0.8167531 | H29: =Financials!H6/((Financials!H26+Financials!G26)/2) -> 0.77457815 | I29: =Financials!I6/((Financials!I26+Financials!H26)/2) -> 0.80786461 | J29: =AVERAGE(E29:I29) -> 0.79926278
A30: HUL | B30: × Equity Multiplier | C30: Average Total Assets / Average Equity | D30: n/a | E30: =((Financials!E26+Financials!D26)/2)/((Financials!E37+Financials!D37)/2) -> 1.4394583 | F30: =((Financials!F26+Financials!E26)/2)/((Financials!F37+Financials!E37)/2) -> 1.4450058 | G30: =((Financials!G26+Financials!F26)/2)/((Financials!G37+Financials!F37)/2) -> 1.4929375 | H30: =((Financials!H26+Financials!G26)/2)/((Financials!H37+Financials!G37)/2) -> 1.5737627 | I30: =((Financials!I26+Financials!H26)/2)/((Financials!I37+Financials!H37)/2) -> 1.6262418 | J30: =AVERAGE(E30:I30) -> 1.5154812
A31: HUL | B31: ROE (DuPont product) | C31: Product of the three components; should equal ROE above | D31: n/a | E31: =E28*E29*E30 -> 0.18384246 | F31: =F28*F29*F30 -> 0.20415639 | G31: =G28*G29*G30 -> 0.20255708 | H31: =H28*H29*H30 -> 0.21210495 | I31: =I28*I29*I30 -> 0.30688499 | J31: =AVERAGE(E31:I31) -> 0.22190917
A33: ITC | B33: Ratio | C33: Formula | D33: FY21 | E33: FY22 | F33: FY23 | G33: FY24 | H33: FY25 | I33: FY26 | J33: 5Y Avg (FY22–26)
A34: ITC | B34: Growth
A35: ITC | B35: Revenue Growth (YoY) | C35: Sales / previous year Sales − 1 | D35: n/a | E35: =Financials!E44/Financials!D44-1 -> 0.23119557 | F35: =Financials!F44/Financials!E44-1 -> 0.16941215 | G35: =Financials!G44/Financials!F44-1 -> -0.042118473 | H35: =Financials!H44/Financials!G44-1 -> 0.10879998 | I35: =Financials!I44/Financials!H44-1 -> 0.047063978 | J35: =AVERAGE(E35:I35) -> 0.10287064
A36: ITC | B36: Net Profit Growth (YoY) | C36: Net Profit / previous year Net Profit − 1 | D36: n/a | E36: =Financials!E51/Financials!D51-1 -> 0.15840992 | F36: =Financials!F51/Financials!E51-1 -> 0.25633748 | G36: =Financials!G51/Financials!F51-1 -> 0.065410484 | H36: =Financials!H51/Financials!G51-1 -> 0.68917161 | I36: =Financials!I51/Financials!H51-1 -> -0.40037658 | J36: =AVERAGE(E36:I36) -> 0.15379058
A37: ITC | B37: Profitability
A38: ITC | B38: Operating Margin (OPM) | C38: Operating Profit / Sales | D38: =Financials!D46/Financials!D44 -> 0.34644822 | E38: =Financials!E46/Financials!E44 -> 0.34006101 | F38: =Financials!F46/Financials!F44 -> 0.36244166 | G38: =Financials!G46/Financials!G44 -> 0.37078255 | H38: =Financials!H46/Financials!H44 -> 0.3429497 | I38: =Financials!I46/Financials!I44 -> 0.34622407 | J38: =AVERAGE(E38:I38) -> 0.3524918
A39: ITC | B39: Net Profit Margin | C39: Net Profit / Sales | D39: =Financials!D51/Financials!D44 -> 0.27169742 | E39: =Financials!E51/Financials!E44 -> 0.25563525 | F39: =Financials!F51/Financials!F44 -> 0.27463726 | G39: =Financials!G51/Financials!G44 -> 0.30546723 | H39: =Financials!H51/Financials!H44 -> 0.46535587 | I39: =Financials!I51/Financials!I44 -> 0.26649592 | J39: =AVERAGE(E39:I39) -> 0.31351831
A40: ITC | B40: Return on Equity (ROE) | C40: Net Profit / Average Shareholders' Equity | D40: n/a | E40: =Financials!E51/((Financials!E75+Financials!D75)/2) -> 0.25248774 | F40: =Financials!F51/((Financials!F75+Financials!E75)/2) -> 0.29598055 | G40: =Financials!G51/((Financials!G75+Financials!F75)/2) -> 0.28888641 | H40: =Financials!H51/((Financials!H75+Financials!G75)/2) -> 0.4850246 | I40: =Financials!I51/((Financials!I75+Financials!H75)/2) -> 0.2949129 | J40: =AVERAGE(E40:I40) -> 0.32345844
A41: ITC | B41: Return on Capital Employed (ROCE) | C41: EBIT / Average Capital Employed | D41: n/a | E41: =Financials!E76/((Financials!E77+Financials!D77)/2) -> 0.3373283 | F41: =Financials!F76/((Financials!F77+Financials!E77)/2) -> 0.39334166 | G41: =Financials!G76/((Financials!G77+Financials!F77)/2) -> 0.3742956 | H41: =Financials!H76/((Financials!H77+Financials!G77)/2) -> 0.57864599 | I41: =Financials!I76/((Financials!I77+Financials!H77)/2) -> 0.38724427 | J41: =AVERAGE(E41:I41) -> 0.41417116
A42: ITC | B42: Return on Assets (ROA) | C42: Net Profit / Average Total Assets | D42: n/a | E42: =Financials!E51/((Financials!E64+Financials!D64)/2) -> 0.20539624 | F42: =Financials!F51/((Financials!F64+Financials!E64)/2) -> 0.23894202 | G42: =Financials!G51/((Financials!G64+Financials!F64)/2) -> 0.23370349 | H42: =Financials!H51/((Financials!H64+Financials!G64)/2) -> 0.38999316 | I42: =Financials!I51/((Financials!I64+Financials!H64)/2) -> 0.2314248 | J42: =AVERAGE(E42:I42) -> 0.25989194
A43: ITC | B43: Efficiency
A44: ITC | B44: Asset Turnover | C44: Sales / Average Total Assets | D44: n/a | E44: =Financials!E44/((Financials!E64+Financials!D64)/2) -> 0.80347384 | F44: =Financials!F44/((Financials!F64+Financials!E64)/2) -> 0.87002766 | G44: =Financials!G44/((Financials!G64+Financials!F64)/2) -> 0.76506893 | H44: =Financials!H44/((Financials!H64+Financials!G64)/2) -> 0.83805359 | I44: =Financials!I44/((Financials!I64+Financials!H64)/2) -> 0.86839903 | J44: =AVERAGE(E44:I44) -> 0.82900461
A45: ITC | B45: Debtor Days | C45: As reported | D45: =Financials!D71 -> 19 | E45: =Financials!E71 -> 15 | F45: =Financials!F71 -> 15 | G45: =Financials!G71 -> 22 | H45: =Financials!H71 -> 23 | I45: =Financials!I71 -> 18 | J45: =AVERAGE(E45:I45) -> 18.6
A46: ITC | B46: Inventory Days | C46: As reported | D46: =Financials!D72 -> 189 | E46: =Financials!E72 -> 150 | F46: =Financials!F72 -> 148 | G46: =Financials!G72 -> 191 | H46: =Financials!H72 -> 178 | I46: =Financials!I72 -> 209 | J46: =AVERAGE(E46:I46) -> 175.2
A47: ITC | B47: Payable Days | C47: As reported | D47: =Financials!D73 -> 78 | E47: =Financials!E73 -> 61 | F47: =Financials!F73 -> 59 | G47: =Financials!G73 -> 65 | H47: =Financials!H73 -> 55 | I47: =Financials!I73 -> 63 | J47: =AVERAGE(E47:I47) -> 60.6
A48: ITC | B48: Cash Conversion Cycle (days) | C48: Debtor Days + Inventory Days − Payable Days | D48: =D45+D46-D47 -> 130 | E48: =E45+E46-E47 -> 104 | F48: =F45+F46-F47 -> 104 | G48: =G45+G46-G47 -> 148 | H48: =H45+H46-H47 -> 146 | I48: =I45+I46-I47 -> 164 | J48: =AVERAGE(E48:I48) -> 133.2
A49: ITC | B49: Leverage & Coverage
A50: ITC | B50: Debt / Equity | C50: Borrowings / Shareholders' Equity (year-end) | D50: =Financials!D57/Financials!D75 -> 0.0044906955 | E50: =Financials!E57/Financials!E75 -> 0.0039868705 | F50: =Financials!F57/Financials!F75 -> 0.0044248427 | G50: =Financials!G57/Financials!G75 -> 0.004066732 | H50: =Financials!H57/Financials!H75 -> 0.0040696844 | I50: =Financials!I57/Financials!I75 -> 0.033086461 | J50: =AVERAGE(E50:I50) -> 0.0099269181
A51: ITC | B51: Interest Coverage | C51: EBIT / Interest | D51: =IFERROR(Financials!D76/Financials!D48,0) -> 310.27586 | E51: =IFERROR(Financials!E76/Financials!E48,0) -> 346.66667 | F51: =IFERROR(Financials!F76/Financials!F48,0) -> 333.24359 | G51: =IFERROR(Financials!G76/Financials!G48,0) -> 692.30769 | H51: =IFERROR(Financials!H76/Financials!H48,0) -> 933.06667 | I51: =IFERROR(Financials!I76/Financials!I48,0) -> 330.8 | J51: =AVERAGE(E51:I51) -> 527.21692
A52: ITC | B52: Cash Flow & Payout
A53: ITC | B53: CFO / Net Profit (earnings quality) | C53: Cash from Operations / Net Profit | D53: =Financials!D66/Financials!D51 -> 0.93603826 | E53: =Financials!E66/Financials!E51 -> 1.0176095 | F53: =Financials!F66/Financials!F51 -> 0.96924578 | G53: =Financials!G66/Financials!G51 -> 0.82786372 | H53: =Financials!H66/Financials!H51 -> 0.50288143 | I53: =Financials!I66/Financials!I51 -> 0.87848511 | J53: =AVERAGE(E53:I53) -> 0.83921711
A54: ITC | B54: Free Cash Flow Margin | C54: Free Cash Flow / Sales | D54: =Financials!D69/Financials!D44 -> 0.2170859 | E54: =Financials!E69/Financials!E44 -> 0.22700965 | F54: =Financials!F69/Financials!F44 -> 0.22820401 | G54: =Financials!G69/Financials!G44 -> 0.20202555 | H54: =Financials!H69/Financials!H44 -> 0.20609907 | I54: =Financials!I69/Financials!I44 -> 0.20708018 | J54: =AVERAGE(E54:I54) -> 0.21408369
A55: ITC | B55: Dividend Payout | C55: As reported | D55: =Financials!D53 -> 1.01 | E55: =Financials!E53 -> 0.93 | F55: =Financials!F53 -> 1 | G55: =Financials!G53 -> 0.84 | H55: =Financials!H53 -> 0.52 | I55: =Financials!I53 -> 0.88 | J55: =AVERAGE(E55:I55) -> 0.834
A56: ITC | B56: DuPont Analysis of ROE
A57: ITC | B57: Net Profit Margin | C57: Net Profit / Sales | D57: =Financials!D51/Financials!D44 -> 0.27169742 | E57: =Financials!E51/Financials!E44 -> 0.25563525 | F57: =Financials!F51/Financials!F44 -> 0.27463726 | G57: =Financials!G51/Financials!G44 -> 0.30546723 | H57: =Financials!H51/Financials!H44 -> 0.46535587 | I57: =Financials!I51/Financials!I44 -> 0.26649592 | J57: =AVERAGE(E57:I57) -> 0.31351831
A58: ITC | B58: × Asset Turnover | C58: Sales / Average Total Assets | D58: n/a | E58: =Financials!E44/((Financials!E64+Financials!D64)/2) -> 0.80347384 | F58: =Financials!F44/((Financials!F64+Financials!E64)/2) -> 0.87002766 | G58: =Financials!G44/((Financials!G64+Financials!F64)/2) -> 0.76506893 | H58: =Financials!H44/((Financials!H64+Financials!G64)/2) -> 0.83805359 | I58: =Financials!I44/((Financials!I64+Financials!H64)/2) -> 0.86839903 | J58: =AVERAGE(E58:I58) -> 0.82900461
A59: ITC | B59: × Equity Multiplier | C59: Average Total Assets / Average Equity | D59: n/a | E59: =((Financials!E64+Financials!D64)/2)/((Financials!E75+Financials!D75)/2) -> 1.2292715 | F59: =((Financials!F64+Financials!E64)/2)/((Financials!F75+Financials!E75)/2) -> 1.2387129 | G59: =((Financials!G64+Financials!F64)/2)/((Financials!G75+Financials!F75)/2) -> 1.2361237 | H59: =((Financials!H64+Financials!G64)/2)/((Financials!H75+Financials!G75)/2) -> 1.2436746 | I59: =((Financials!I64+Financials!H64)/2)/((Financials!I75+Financials!H75)/2) -> 1.2743358 | J59: =AVERAGE(E59:I59) -> 1.2444237
A60: ITC | B60: ROE (DuPont product) | C60: Product of the three components; should equal ROE above | D60: n/a | E60: =E57*E58*E59 -> 0.25248774 | F60: =F57*F58*F59 -> 0.29598055 | G60: =G57*G58*G59 -> 0.28888641 | H60: =H57*H58*H59 -> 0.4850246 | I60: =I57*I58*I59 -> 0.2949129 | J60: =AVERAGE(E60:I60) -> 0.32345844
A62: Dabur | B62: Ratio | C62: Formula | D62: FY21 | E62: FY22 | F62: FY23 | G62: FY24 | H62: FY25 | I62: FY26 | J62: 5Y Avg (FY22–26)
A63: Dabur | B63: Growth
A64: Dabur | B64: Revenue Growth (YoY) | C64: Sales / previous year Sales − 1 | D64: n/a | E64: =Financials!E82/Financials!D82-1 -> 0.1387785 | F64: =Financials!F82/Financials!E82-1 -> 0.058866746 | G64: =Financials!G82/Financials!F82-1 -> 0.075802255 | H64: =Financials!H82/Financials!G82-1 -> 0.012818446 | I64: =Financials!I82/Financials!H82-1 -> 0.050147258 | J64: =AVERAGE(E64:I64) -> 0.067282641
A65: Dabur | B65: Net Profit Growth (YoY) | C65: Net Profit / previous year Net Profit − 1 | D65: n/a | E65: =Financials!E89/Financials!D89-1 -> 0.027728614 | F65: =Financials!F89/Financials!E89-1 -> -0.023536165 | G65: =Financials!G89/Financials!F89-1 -> 0.064667842 | H65: =Financials!H89/Financials!G89-1 -> -0.039204859 | I65: =Financials!I89/Financials!H89-1 -> 0.074137931 | J65: =AVERAGE(E65:I65) -> 0.020758673
A66: Dabur | B66: Profitability
A67: Dabur | B67: Operating Margin (OPM) | C67: Operating Profit / Sales | D67: =Financials!D84/Financials!D82 -> 0.20937042 | E67: =Financials!E84/Financials!E82 -> 0.20681422 | F67: =Financials!F84/Financials!F82 -> 0.18751084 | G67: =Financials!G84/Financials!G82 -> 0.19348597 | H67: =Financials!H84/Financials!H82 -> 0.18435087 | I67: =Financials!I84/Financials!I82 -> 0.18570454 | J67: =AVERAGE(E67:I67) -> 0.19157329
A68: Dabur | B68: Net Profit Margin | C68: Net Profit / Sales | D68: =Financials!D89/Financials!D82 -> 0.17726417 | E68: =Financials!E89/Financials!E82 -> 0.15997796 | F68: =Financials!F89/Financials!F82 -> 0.14752819 | G68: =Financials!G89/Financials!G82 -> 0.14600129 | H68: =Financials!H89/Financials!H82 -> 0.13850195 | I68: =Financials!I89/Financials!I82 -> 0.14166604 | J68: =AVERAGE(E68:I68) -> 0.14673508
A69: Dabur | B69: Return on Equity (ROE) | C69: Net Profit / Average Shareholders' Equity | D69: n/a | E69: =Financials!E89/((Financials!E113+Financials!D113)/2) -> 0.21712576 | F69: =Financials!F89/((Financials!F113+Financials!E113)/2) -> 0.1960242 | G69: =Financials!G89/((Financials!G113+Financials!F113)/2) -> 0.19226074 | H69: =Financials!H89/((Financials!H113+Financials!G113)/2) -> 0.16839253 | I69: =Financials!I89/((Financials!I113+Financials!H113)/2) -> 0.16823439 | J69: =AVERAGE(E69:I69) -> 0.18840752
A70: Dabur | B70: Return on Capital Employed (ROCE) | C70: EBIT / Average Capital Employed | D70: n/a | E70: =Financials!E114/((Financials!E115+Financials!D115)/2) -> 0.26249645 | F70: =Financials!F114/((Financials!F115+Financials!E115)/2) -> 0.23487908 | G70: =Financials!G114/((Financials!G115+Financials!F115)/2) -> 0.23229488 | H70: =Financials!H114/((Financials!H115+Financials!G115)/2) -> 0.21078282 | I70: =Financials!I114/((Financials!I115+Financials!H115)/2) -> 0.20976447 | J70: =AVERAGE(E70:I70) -> 0.23004354
A71: Dabur | B71: Return on Assets (ROA) | C71: Net Profit / Average Total Assets | D71: n/a | E71: =Financials!E89/((Financials!E102+Financials!D102)/2) -> 0.15070508 | F71: =Financials!F89/((Financials!F102+Financials!E102)/2) -> 0.13116397 | G71: =Financials!G89/((Financials!G102+Financials!F102)/2) -> 0.12590378 | H71: =Financials!H89/((Financials!H102+Financials!G102)/2) -> 0.11101895 | I71: =Financials!I89/((Financials!I102+Financials!H102)/2) -> 0.11088698 | J71: =AVERAGE(E71:I71) -> 0.12593575
A72: Dabur | B72: Efficiency
A73: Dabur | B73: Asset Turnover | C73: Sales / Average Total Assets | D73: n/a | E73: =Financials!E82/((Financials!E102+Financials!D102)/2) -> 0.94203651 | F73: =Financials!F82/((Financials!F102+Financials!E102)/2) -> 0.88907738 | G73: =Financials!G82/((Financials!G102+Financials!F102)/2) -> 0.86234705 | H73: =Financials!H82/((Financials!H102+Financials!G102)/2) -> 0.80156958 | I73: =Financials!I82/((Financials!I102+Financials!H102)/2) -> 0.78273509 | J73: =AVERAGE(E73:I73) -> 0.85555312
A74: Dabur | B74: Debtor Days | C74: As reported | D74: =Financials!D109 -> 21 | E74: =Financials!E109 -> 22 | F74: =Financials!F109 -> 27 | G74: =Financials!G109 -> 26 | H74: =Financials!H109 -> 26 | I74: =Financials!I109 -> 20 | J74: =AVERAGE(E74:I74) -> 24.2
A75: Dabur | B75: Inventory Days | C75: As reported | D75: =Financials!D110 -> 178 | E75: =Financials!E110 -> 169 | F75: =Financials!F110 -> 158 | G75: =Financials!G110 -> 149 | H75: =Financials!H110 -> 175 | I75: =Financials!I110 -> 166 | J75: =AVERAGE(E75:I75) -> 163.4
A76: Dabur | B76: Payable Days | C76: As reported | D76: =Financials!D111 -> 197 | E76: =Financials!E111 -> 178 | F76: =Financials!F111 -> 171 | G76: =Financials!G111 -> 186 | H76: =Financials!H111 -> 215 | I76: =Financials!I111 -> 212 | J76: =AVERAGE(E76:I76) -> 192.4
A77: Dabur | B77: Cash Conversion Cycle (days) | C77: Debtor Days + Inventory Days − Payable Days | D77: =D74+D75-D76 -> 2 | E77: =E74+E75-E76 -> 13 | F77: =F74+F75-F76 -> 14 | G77: =G74+G75-G76 -> -11 | H77: =H74+H75-H76 -> -14 | I77: =I74+I75-I76 -> -26 | J77: =AVERAGE(E77:I77) -> -4.8
A78: Dabur | B78: Leverage & Coverage
A79: Dabur | B79: Debt / Equity | C79: Borrowings / Shareholders' Equity (year-end) | D79: =Financials!D95/Financials!D113 -> 0.066414405 | E79: =Financials!E95/Financials!E113 -> 0.12288237 | F79: =Financials!F95/Financials!F113 -> 0.13083696 | G79: =Financials!G95/Financials!G113 -> 0.13835394 | H79: =Financials!H95/Financials!H113 -> 0.087962963 | I79: =Financials!I95/Financials!I113 -> 0.11270689 | J79: =AVERAGE(E79:I79) -> 0.11854862
A80: Dabur | B80: Interest Coverage | C80: EBIT / Interest | D80: =IFERROR(Financials!D114/Financials!D86,0) -> 67.322581 | E80: =IFERROR(Financials!E114/Financials!E86,0) -> 59.179487 | F80: =IFERROR(Financials!F114/Financials!F86,0) -> 29.448718 | G80: =IFERROR(Financials!G114/Financials!G86,0) -> 20.024194 | H80: =IFERROR(Financials!H114/Financials!H86,0) -> 14.768293 | I80: =IFERROR(Financials!I114/Financials!I86,0) -> 17.689655 | J80: =AVERAGE(E80:I80) -> 28.222069
A81: Dabur | B81: Cash Flow & Payout
A82: Dabur | B82: CFO / Net Profit (earnings quality) | C82: Cash from Operations / Net Profit | D82: =Financials!D104/Financials!D89 -> 1.2477876 | E82: =Financials!E104/Financials!E89 -> 1.0344432 | F82: =Financials!F104/Financials!F89 -> 0.87477954 | G82: =Financials!G104/Financials!G89 -> 1.1115406 | H82: =Financials!H104/Financials!H89 -> 1.141954 | I82: =Financials!I104/Financials!I89 -> 1.3798823 | J82: =AVERAGE(E82:I82) -> 1.1085199
A83: Dabur | B83: Free Cash Flow Margin | C83: Free Cash Flow / Sales | D83: =Financials!D107/Financials!D82 -> 0.18908178 | E83: =Financials!E107/Financials!E82 -> 0.1316007 | F83: =Financials!F107/Financials!F82 -> 0.08699046 | G83: =Financials!G107/Financials!G82 -> 0.11713963 | H83: =Financials!H107/Financials!H82 -> 0.11525909 | I83: =Financials!I107/Financials!I82 -> 0.16523914 | J83: =AVERAGE(E83:I83) -> 0.12324581
A84: Dabur | B84: Dividend Payout | C84: As reported | D84: =Financials!D91 -> 0.5 | E84: =Financials!E91 -> 0.53 | F84: =Financials!F91 -> 0.54 | G84: =Financials!G91 -> 0.53 | H84: =Financials!H91 -> 0.8 | I84: =Financials!I91 -> 0.77 | J84: =AVERAGE(E84:I84) -> 0.634
A85: Dabur | B85: DuPont Analysis of ROE
A86: Dabur | B86: Net Profit Margin | C86: Net Profit / Sales | D86: =Financials!D89/Financials!D82 -> 0.17726417 | E86: =Financials!E89/Financials!E82 -> 0.15997796 | F86: =Financials!F89/Financials!F82 -> 0.14752819 | G86: =Financials!G89/Financials!G82 -> 0.14600129 | H86: =Financials!H89/Financials!H82 -> 0.13850195 | I86: =Financials!I89/Financials!I82 -> 0.14166604 | J86: =AVERAGE(E86:I86) -> 0.14673508
A87: Dabur | B87: × Asset Turnover | C87: Sales / Average Total Assets | D87: n/a | E87: =Financials!E82/((Financials!E102+Financials!D102)/2) -> 0.94203651 | F87: =Financials!F82/((Financials!F102+Financials!E102)/2) -> 0.88907738 | G87: =Financials!G82/((Financials!G102+Financials!F102)/2) -> 0.86234705 | H87: =Financials!H82/((Financials!H102+Financials!G102)/2) -> 0.80156958 | I87: =Financials!I82/((Financials!I102+Financials!H102)/2) -> 0.78273509 | J87: =AVERAGE(E87:I87) -> 0.85555312
A88: Dabur | B88: × Equity Multiplier | C88: Average Total Assets / Average Equity | D88: n/a | E88: =((Financials!E102+Financials!D102)/2)/((Financials!E113+Financials!D113)/2) -> 1.4407329 | F88: =((Financials!F102+Financials!E102)/2)/((Financials!F113+Financials!E113)/2) -> 1.4944973 | G88: =((Financials!G102+Financials!F102)/2)/((Financials!G113+Financials!F113)/2) -> 1.527045 | H88: =((Financials!H102+Financials!G102)/2)/((Financials!H113+Financials!G113)/2) -> 1.5167909 | I88: =((Financials!I102+Financials!H102)/2)/((Financials!I113+Financials!H113)/2) -> 1.51717 | J88: =AVERAGE(E88:I88) -> 1.4992472
A89: Dabur | B89: ROE (DuPont product) | C89: Product of the three components; should equal ROE above | D89: n/a | E89: =E86*E87*E88 -> 0.21712576 | F89: =F86*F87*F88 -> 0.1960242 | G89: =G86*G87*G88 -> 0.19226074 | H89: =H86*H87*H88 -> 0.16839253 | I89: =I86*I87*I88 -> 0.16823439 | J89: =AVERAGE(E89:I89) -> 0.18840752
A91: Britannia | B91: Ratio | C91: Formula | D91: FY21 | E91: FY22 | F91: FY23 | G91: FY24 | H91: FY25 | I91: FY26 | J91: 5Y Avg (FY22–26)
A92: Britannia | B92: Growth
A93: Britannia | B93: Revenue Growth (YoY) | C93: Sales / previous year Sales − 1 | D93: n/a | E93: =Financials!E120/Financials!D120-1 -> 0.076126675 | F93: =Financials!F120/Financials!E120-1 -> 0.15315507 | G93: =Financials!G120/Financials!F120-1 -> 0.028709895 | H93: =Financials!H120/Financials!G120-1 -> 0.070010138 | I93: =Financials!I120/Financials!H120-1 -> 0.067380037 | J93: =AVERAGE(E93:I93) -> 0.079076362
A94: Britannia | B94: Net Profit Growth (YoY) | C94: Net Profit / previous year Net Profit − 1 | D94: n/a | E94: =Financials!E127/Financials!D127-1 -> -0.18098325 | F94: =Financials!F127/Financials!E127-1 -> 0.52770449 | G94: =Financials!G127/Financials!F127-1 -> -0.078583765 | H94: =Financials!H127/Financials!G127-1 -> 0.020618557 | I94: =Financials!I127/Financials!H127-1 -> 0.16483012 | J94: =AVERAGE(E94:I94) -> 0.090717229
A95: Britannia | B95: Profitability
A96: Britannia | B96: Operating Margin (OPM) | C96: Operating Profit / Sales | D96: =Financials!D122/Financials!D120 -> 0.19100183 | E96: =Financials!E122/Financials!E120 -> 0.15570175 | F96: =Financials!F122/Financials!F120 -> 0.17367033 | G96: =Financials!G122/Financials!G120 -> 0.1888604 | H96: =Financials!H122/Financials!H120 -> 0.17700496 | I96: =Financials!I122/Financials!I120 -> 0.18347953 | J96: =AVERAGE(E96:I96) -> 0.17574339
A97: Britannia | B97: Net Profit Margin | C97: Net Profit / Sales | D97: =Financials!D127/Financials!D120 -> 0.14091048 | E97: =Financials!E127/Financials!E120 -> 0.10724392 | F97: =Financials!F127/Financials!F120 -> 0.14207717 | G97: =Financials!G127/Financials!G120 -> 0.12725863 | H97: =Financials!H127/Financials!H120 -> 0.12138438 | I97: =Financials!I127/Financials!I120 -> 0.13246658 | J97: =AVERAGE(E97:I97) -> 0.12608614
A98: Britannia | B98: Return on Equity (ROE) | C98: Net Profit / Average Shareholders' Equity | D98: n/a | E98: =Financials!E127/((Financials!E151+Financials!D151)/2) -> 0.49656076 | F98: =Financials!F127/((Financials!F151+Financials!E151)/2) -> 0.76034143 | G98: =Financials!G127/((Financials!G151+Financials!F151)/2) -> 0.5709699 | H98: =Financials!H127/((Financials!H151+Financials!G151)/2) -> 0.52500904 | I98: =Financials!I127/((Financials!I151+Financials!H151)/2) -> 0.53625026 | J98: =AVERAGE(E98:I98) -> 0.57782628
A99: Britannia | B99: Return on Capital Employed (ROCE) | C99: EBIT / Average Capital Employed | D99: n/a | E99: =Financials!E152/((Financials!E153+Financials!D153)/2) -> 0.41556013 | F99: =Financials!F152/((Financials!F153+Financials!E153)/2) -> 0.55350043 | G99: =Financials!G152/((Financials!G153+Financials!F153)/2) -> 0.49086703 | H99: =Financials!H152/((Financials!H153+Financials!G153)/2) -> 0.52821087 | I99: =Financials!I152/((Financials!I153+Financials!H153)/2) -> 0.56282571 | J99: =AVERAGE(E99:I99) -> 0.51019283
A100: Britannia | B100: Return on Assets (ROA) | C100: Net Profit / Average Total Assets | D100: n/a | E100: =Financials!E127/((Financials!E140+Financials!D140)/2) -> 0.19527275 | F100: =Financials!F127/((Financials!F140+Financials!E140)/2) -> 0.27447262 | G100: =Financials!G127/((Financials!G140+Financials!F140)/2) -> 0.23167951 | H100: =Financials!H127/((Financials!H140+Financials!G140)/2) -> 0.24324324 | I100: =Financials!I127/((Financials!I140+Financials!H140)/2) -> 0.27328055 | J100: =AVERAGE(E100:I100) -> 0.24358974
A101: Britannia | B101: Efficiency
A102: Britannia | B102: Asset Turnover | C102: Sales / Average Total Assets | D102: n/a | E102: =Financials!E120/((Financials!E140+Financials!D140)/2) -> 1.8208282 | F102: =Financials!F120/((Financials!F140+Financials!E140)/2) -> 1.9318559 | G102: =Financials!G120/((Financials!G140+Financials!F140)/2) -> 1.8205407 | H102: =Financials!H120/((Financials!H140+Financials!G140)/2) -> 2.0039089 | I102: =Financials!I120/((Financials!I140+Financials!H140)/2) -> 2.063015 | J102: =AVERAGE(E102:I102) -> 1.9280297
A103: Britannia | B103: Debtor Days | C103: As reported | D103: =Financials!D147 -> 7 | E103: =Financials!E147 -> 9 | F103: =Financials!F147 -> 7 | G103: =Financials!G147 -> 9 | H103: =Financials!H147 -> 9 | I103: =Financials!I147 -> 9 | J103: =AVERAGE(E103:I103) -> 8.6
A104: Britannia | B104: Inventory Days | C104: As reported | D104: =Financials!D148 -> 52 | E104: =Financials!E148 -> 57 | F104: =Financials!F148 -> 45 | G104: =Financials!G148 -> 45 | H104: =Financials!H148 -> 43 | I104: =Financials!I148 -> 44 | J104: =AVERAGE(E104:I104) -> 46.8
...

Sheet Comparison
A1: Peer Comparison
A2: Linked to the Ratios and Financials sheets. Rank 1 = best (for Debt/Equity and Cash Conversion Cycle, lower is better).
A4: FY26 Snapshot
A5: Metric | B5: HUL | C5: ITC | D5: Dabur | E5: Britannia | F5: Marico
A6: Revenue CAGR (FY21–FY26) | B6: =(Financials!I6/Financials!D6)^(1/5)-1 -> 0.065117542 | C6: =(Financials!I44/Financials!D44)^(1/5)-1 -> 0.098718846 | D6: =(Financials!I82/Financials!D82)^(1/5)-1 -> 0.066495346 | E6: =(Financials!I120/Financials!D120)^(1/5)-1 -> 0.078326303 | F6: =(Financials!I158/Financials!D158)^(1/5)-1 -> 0.11081162
A7: Net Profit CAGR (FY21–FY26) | B7: =(Financials!I13/Financials!D13)^(1/5)-1 -> 0.1348856 | C7: =(Financials!I51/Financials!D51)^(1/5)-1 -> 0.094479375 | D7: =(Financials!I89/Financials!D89)^(1/5)-1 -> 0.019736395 | E7: =(Financials!I127/Financials!D127)^(1/5)-1 -> 0.065081423 | F7: =(Financials!I165/Financials!D165)^(1/5)-1 -> 0.086214821
A8: Operating Margin | B8: =Ratios!I9 -> 0.23327853 | C8: =Ratios!I38 -> 0.34622407 | D8: =Ratios!I67 -> 0.18570454 | E8: =Ratios!I96 -> 0.18347953 | F8: =Ratios!I125 -> 0.17103813
A9: Net Profit Margin | B9: =Ratios!I10 -> 0.23358876 | C9: =Ratios!I39 -> 0.26649592 | D9: =Ratios!I68 -> 0.14166604 | E9: =Ratios!I97 -> 0.13246658 | F9: =Ratios!I126 -> 0.13320109
A10: ROE | B10: =Ratios!I11 -> 0.30688499 | C10: =Ratios!I40 -> 0.2949129 | D10: =Ratios!I69 -> 0.16823439 | E10: =Ratios!I98 -> 0.53625026 | F10: =Ratios!I127 -> 0.4430055
A11: ROCE | B11: =Ratios!I12 -> 0.36791847 | C11: =Ratios!I41 -> 0.38724427 | D11: =Ratios!I70 -> 0.20976447 | E11: =Ratios!I99 -> 0.56282571 | F11: =Ratios!I128 -> 0.50129088
A12: ROA | B12: =Ratios!I13 -> 0.18870809 | C12: =Ratios!I42 -> 0.2314248 | D12: =Ratios!I71 -> 0.11088698 | E12: =Ratios!I100 -> 0.27328055 | F12: =Ratios!I129 -> 0.19895748
A13: Asset Turnover | B13: =Ratios!I15 -> 0.80786461 | C13: =Ratios!I44 -> 0.86839903 | D13: =Ratios!I73 -> 0.78273509 | E13: =Ratios!I102 -> 2.063015 | F13: =Ratios!I131 -> 1.4936626
A14: Cash Conversion Cycle (days) | B14: =Ratios!I19 -> -89 | C14: =Ratios!I48 -> 164 | D14: =Ratios!I77 -> -26 | E14: =Ratios!I106 -> -9 | F14: =Ratios!I135 -> 12
A15: Debt / Equity | B15: =Ratios!I21 -> 0.030324791 | C15: =Ratios!I50 -> 0.033086461 | D15: =Ratios!I79 -> 0.11270689 | E15: =Ratios!I108 -> 0.27027027 | F15: =Ratios!I137 -> 0.13230404
A16: Interest Coverage | B16: =Ratios!I22 -> 45.436585 | C16: =Ratios!I51 -> 330.8 | D16: =Ratios!I80 -> 17.689655 | E16: =Ratios!I109 -> 30.106195 | F16: =Ratios!I138 -> 43.962264
A17: CFO / Net Profit | B17: =Ratios!I24 -> 0.73039378 | C17: =Ratios!I53 -> 0.87848511 | D17: =Ratios!I82 -> 1.3798823 | E17: =Ratios!I111 -> 1.0295625 | F17: =Ratios!I140 -> 1.149476
A18: Free Cash Flow Margin | B18: =Ratios!I25 -> 0.14995036 | C18: =Ratios!I54 -> 0.20708018 | D18: =Ratios!I83 -> 0.16523914 | E18: =Ratios!I112 -> 0.12573099 | F18: =Ratios!I141 -> 0.13018882
A19: Dividend Payout | B19: =Ratios!I26 -> 0.64 | C19: =Ratios!I55 -> 0.88 | D19: =Ratios!I84 -> 0.77 | E19: =Ratios!I113 -> 0.86 | F19: =Ratios!I142 -> 0.3
A22: 5-Year Average (FY22–FY26)
A23: Metric | B23: HUL | C23: ITC | D23: Dabur | E23: Britannia | F23: Marico
A24: Operating Margin | B24: =Ratios!J9 -> 0.23768935 | C24: =Ratios!J38 -> 0.3524918 | D24: =Ratios!J67 -> 0.19157329 | E24: =Ratios!J96 -> 0.17574339 | F24: =Ratios!J125 -> 0.18810175
A25: Net Profit Margin | B25: =Ratios!J10 -> 0.18213645 | C25: =Ratios!J39 -> 0.31351831 | D25: =Ratios!J68 -> 0.14673508 | E25: =Ratios!J97 -> 0.12608614 | F25: =Ratios!J126 -> 0.14184269
A26: ROE | B26: =Ratios!J11 -> 0.22190917 | C26: =Ratios!J40 -> 0.32345844 | D26: =Ratios!J69 -> 0.18840752 | E26: =Ratios!J98 -> 0.57782628 | F26: =Ratios!J127 -> 0.40247023
A27: ROCE | B27: =Ratios!J12 -> 0.2873702 | C27: =Ratios!J41 -> 0.41417116 | D27: =Ratios!J70 -> 0.23004354 | E27: =Ratios!J99 -> 0.51019283 | F27: =Ratios!J128 -> 0.4635296
A28: ROA | B28: =Ratios!J13 -> 0.14563224 | C28: =Ratios!J42 -> 0.25989194 | D28: =Ratios!J71 -> 0.12593575 | E28: =Ratios!J100 -> 0.24358974 | F28: =Ratios!J129 -> 0.2122735
A29: Asset Turnover | B29: =Ratios!J15 -> 0.79926278 | C29: =Ratios!J44 -> 0.82900461 | D29: =Ratios!J73 -> 0.85555312 | E29: =Ratios!J102 -> 1.9280297 | F29: =Ratios!J131 -> 1.5044775
A30: Cash Conversion Cycle (days) | B30: =Ratios!J19 -> -68.8 | C30: =Ratios!J48 -> 133.2 | D30: =Ratios!J77 -> -4.8 | E30: =Ratios!J106 -> -3.6 | F30: =Ratios!J135 -> 22.8
A31: Debt / Equity | B31: =Ratios!J21 -> 0.027629973 | C31: =Ratios!J50 -> 0.0099269181 | D31: =Ratios!J79 -> 0.11854862 | E31: =Ratios!J108 -> 0.57969333 | F31: =Ratios!J137 -> 0.14251495
A32: Interest Coverage | B32: =Ratios!J22 -> 71.619002 | C32: =Ratios!J51 -> 527.21692 | D32: =Ratios!J80 -> 28.222069 | E32: =Ratios!J109 -> 21.060649 | F32: =Ratios!J138 -> 37.319464
A33: CFO / Net Profit | B33: =Ratios!J24 -> 1.0702572 | C33: =Ratios!J53 -> 0.83921711 | D33: =Ratios!J82 -> 1.1085199 | E33: =Ratios!J111 -> 1.0654365 | F33: =Ratios!J140 -> 0.95558433
A34: Free Cash Flow Margin | B34: =Ratios!J25 -> 0.17004776 | C34: =Ratios!J54 -> 0.21408369 | D34: =Ratios!J83 -> 0.12324581 | E34: =Ratios!J112 -> 0.10750897 | F34: =Ratios!J141 -> 0.11844567
A35: Dividend Payout | B35: =Ratios!J26 -> 0.916 | C35: =Ratios!J55 -> 0.834 | D35: =Ratios!J84 -> 0.634 | E35: =Ratios!J113 -> 0.832 | F35: =Ratios!J142 -> 0.676
A38: FY26 Ranking (1 = best)
A39: Metric | B39: HUL | C39: ITC | D39: Dabur | E39: Britannia | F39: Marico
A40: Revenue CAGR (FY21–FY26) | B40: =RANK(B6,$B$6:$F$6,0) -> 5 | C40: =RANK(C6,$B$6:$F$6,0) -> 2 | D40: =RANK(D6,$B$6:$F$6,0) -> 4 | E40: =RANK(E6,$B$6:$F$6,0) -> 3 | F40: =RANK(F6,$B$6:$F$6,0) -> 1
A41: Net Profit CAGR (FY21–FY26) | B41: =RANK(B7,$B$7:$F$7,0) -> 1 | C41: =RANK(C7,$B$7:$F$7,0) -> 2 | D41: =RANK(D7,$B$7:$F$7,0) -> 5 | E41: =RANK(E7,$B$7:$F$7,0) -> 4 | F41: =RANK(F7,$B$7:$F$7,0) -> 3
A42: Operating Margin | B42: =RANK(B8,$B$8:$F$8,0) -> 2 | C42: =RANK(C8,$B$8:$F$8,0) -> 1 | D42: =RANK(D8,$B$8:$F$8,0) -> 3 | E42: =RANK(E8,$B$8:$F$8,0) -> 4 | F42: =RANK(F8,$B$8:$F$8,0) -> 5
A43: Net Profit Margin | B43: =RANK(B9,$B$9:$F$9,0) -> 2 | C43: =RANK(C9,$B$9:$F$9,0) -> 1 | D43: =RANK(D9,$B$9:$F$9,0) -> 3 | E43: =RANK(E9,$B$9:$F$9,0) -> 5 | F43: =RANK(F9,$B$9:$F$9,0) -> 4
A44: ROE | B44: =RANK(B10,$B$10:$F$10,0) -> 3 | C44: =RANK(C10,$B$10:$F$10,0) -> 4 | D44: =RANK(D10,$B$10:$F$10,0) -> 5 | E44: =RANK(E10,$B$10:$F$10,0) -> 1 | F44: =RANK(F10,$B$10:$F$10,0) -> 2
A45: ROCE | B45: =RANK(B11,$B$11:$F$11,0) -> 4 | C45: =RANK(C11,$B$11:$F$11,0) -> 3 | D45: =RANK(D11,$B$11:$F$11,0) -> 5 | E45: =RANK(E11,$B$11:$F$11,0) -> 1 | F45: =RANK(F11,$B$11:$F$11,0) -> 2
A46: ROA | B46: =RANK(B12,$B$12:$F$12,0) -> 4 | C46: =RANK(C12,$B$12:$F$12,0) -> 2 | D46: =RANK(D12,$B$12:$F$12,0) -> 5 | E46: =RANK(E12,$B$12:$F$12,0) -> 1 | F46: =RANK(F12,$B$12:$F$12,0) -> 3
A47: Asset Turnover | B47: =RANK(B13,$B$13:$F$13,0) -> 4 | C47: =RANK(C13,$B$13:$F$13,0) -> 3 | D47: =RANK(D13,$B$13:$F$13,0) -> 5 | E47: =RANK(E13,$B$13:$F$13,0) -> 1 | F47: =RANK(F13,$B$13:$F$13,0) -> 2
A48: Cash Conversion Cycle (days) | B48: =RANK(B14,$B$14:$F$14,1) -> 1 | C48: =RANK(C14,$B$14:$F$14,1) -> 5 | D48: =RANK(D14,$B$14:$F$14,1) -> 2 | E48: =RANK(E14,$B$14:$F$14,1) -> 3 | F48: =RANK(F14,$B$14:$F$14,1) -> 4
A49: Debt / Equity | B49: =RANK(B15,$B$15:$F$15,1) -> 1 | C49: =RANK(C15,$B$15:$F$15,1) -> 2 | D49: =RANK(D15,$B$15:$F$15,1) -> 3 | E49: =RANK(E15,$B$15:$F$15,1) -> 5 | F49: =RANK(F15,$B$15:$F$15,1) -> 4
A50: Interest Coverage | B50: =RANK(B16,$B$16:$F$16,0) -> 2 | C50: =RANK(C16,$B$16:$F$16,0) -> 1 | D50: =RANK(D16,$B$16:$F$16,0) -> 5 | E50: =RANK(E16,$B$16:$F$16,0) -> 4 | F50: =RANK(F16,$B$16:$F$16,0) -> 3
A51: CFO / Net Profit | B51: =RANK(B17,$B$17:$F$17,0) -> 5 | C51: =RANK(C17,$B$17:$F$17,0) -> 4 | D51: =RANK(D17,$B$17:$F$17,0) -> 1 | E51: =RANK(E17,$B$17:$F$17,0) -> 3 | F51: =RANK(F17,$B$17:$F$17,0) -> 2
A52: Free Cash Flow Margin | B52: =RANK(B18,$B$18:$F$18,0) -> 3 | C52: =RANK(C18,$B$18:$F$18,0) -> 1 | D52: =RANK(D18,$B$18:$F$18,0) -> 2 | E52: =RANK(E18,$B$18:$F$18,0) -> 5 | F52: =RANK(F18,$B$18:$F$18,0) -> 4
A53: Dividend Payout | B53: =RANK(B19,$B$19:$F$19,0) -> 4 | C53: =RANK(C19,$B$19:$F$19,0) -> 1 | D53: =RANK(D19,$B$19:$F$19,0) -> 3 | E53: =RANK(E19,$B$19:$F$19,0) -> 2 | F53: =RANK(F19,$B$19:$F$19,0) -> 5

Sheet Dashboard
A1: FMCG Peer Dashboard
A2: Trend tables (linked to Ratios) feed the charts on the right.
A4: Operating Margin
A5: Year | B5: HUL | C5: ITC | D5: Dabur | E5: Britannia | F5: Marico
A6: FY22 | B6: =Ratios!E9 -> 0.24514739 | C6: =Ratios!E38 -> 0.34006101 | D6: =Ratios!E67 -> 0.20681422 | E6: =Ratios!E96 -> 0.15570175 | F6: =Ratios!E125 -> 0.17672414
A7: FY23 | B7: =Ratios!F9 -> 0.23352592 | C7: =Ratios!F38 -> 0.36244166 | D7: =Ratios!F67 -> 0.18751084 | E7: =Ratios!F96 -> 0.17367033 | F7: =Ratios!F125 -> 0.18537485
A8: FY24 | B8: =Ratios!G9 -> 0.23683275 | C8: =Ratios!G38 -> 0.37078255 | D8: =Ratios!G67 -> 0.19348597 | E8: =Ratios!G96 -> 0.1888604 | F8: =Ratios!G125 -> 0.20988294
A9: FY25 | B9: =Ratios!H9 -> 0.23966214 | C9: =Ratios!H38 -> 0.3429497 | D9: =Ratios!H67 -> 0.18435087 | E9: =Ratios!H96 -> 0.17700496 | F9: =Ratios!H125 -> 0.19748869
A10: FY26 | B10: =Ratios!I9 -> 0.23327853 | C10: =Ratios!I38 -> 0.34622407 | D10: =Ratios!I67 -> 0.18570454 | E10: =Ratios!I96 -> 0.18347953 | F10: =Ratios!I125 -> 0.17103813
A13: ROE
A14: Year | B14: HUL | C14: ITC | D14: Dabur | E14: Britannia | F14: Marico
A15: FY22 | B15: =Ratios!E11 -> 0.18384246 | C15: =Ratios!E40 -> 0.25248774 | D15: =Ratios!E69 -> 0.21712576 | E15: =Ratios!E98 -> 0.49656076 | F15: =Ratios!E127 -> 0.38099575
A16: FY23 | B16: =Ratios!F11 -> 0.20415639 | C16: =Ratios!F40 -> 0.29598055 | D16: =Ratios!F69 -> 0.1960242 | E16: =Ratios!F98 -> 0.76034143 | F16: =Ratios!F127 -> 0.36994543
A17: FY24 | B17: =Ratios!G11 -> 0.20255708 | C17: =Ratios!G40 -> 0.28888641 | D17: =Ratios!G69 -> 0.19226074 | E17: =Ratios!G98 -> 0.5709699 | F17: =Ratios!G127 -> 0.39365745
A18: FY25 | B18: =Ratios!H11 -> 0.21210495 | C18: =Ratios!H40 -> 0.4850246 | D18: =Ratios!H69 -> 0.16839253 | E18: =Ratios!H98 -> 0.52500904 | F18: =Ratios!H127 -> 0.42474702
A19: FY26 | B19: =Ratios!I11 -> 0.30688499 | C19: =Ratios!I40 -> 0.2949129 | D19: =Ratios!I69 -> 0.16823439 | E19: =Ratios!I98 -> 0.53625026 | F19: =Ratios!I127 -> 0.4430055
A22: ROCE
A23: Year | B23: HUL | C23: ITC | D23: Dabur | E23: Britannia | F23: Marico
A24: FY22 | B24: =Ratios!E12 -> 0.24514717 | C24: =Ratios!E41 -> 0.3373283 | D24: =Ratios!E70 -> 0.26249645 | E24: =Ratios!E99 -> 0.41556013 | F24: =Ratios!E128 -> 0.43283188
A25: FY23 | B25: =Ratios!F12 -> 0.26485088 | C25: =Ratios!F41 -> 0.39334166 | D25: =Ratios!F70 -> 0.23487908 | E25: =Ratios!F99 -> 0.55350043 | F25: =Ratios!F128 -> 0.43696867
A26: FY24 | B26: =Ratios!G12 -> 0.27363876 | C26: =Ratios!G41 -> 0.3742956 | D26: =Ratios!G70 -> 0.23229488 | E26: =Ratios!G99 -> 0.49086703 | F26: =Ratios!G128 -> 0.4585377
A27: FY25 | B27: =Ratios!H12 -> 0.28529571 | C27: =Ratios!H41 -> 0.57864599 | D27: =Ratios!H70 -> 0.21078282 | E27: =Ratios!H99 -> 0.52821087 | F27: =Ratios!H128 -> 0.4880189
A28: FY26 | B28: =Ratios!I12 -> 0.36791847 | C28: =Ratios!I41 -> 0.38724427 | D28: =Ratios!I70 -> 0.20976447 | E28: =Ratios!I99 -> 0.56282571 | F28: =Ratios!I128 -> 0.50129088
A31: Revenue Growth (YoY)
A32: Year | B32: HUL | C32: ITC | D32: Dabur | E32: Britannia | F32: Marico
A33: FY22 | B33: =Ratios!E6 -> 0.11520796 | C33: =Ratios!E35 -> 0.23119557 | D33: =Ratios!E64 -> 0.1387785 | E33: =Ratios!E93 -> 0.076126675 | F33: =Ratios!E122 -> 0.18190855
A34: FY23 | B34: =Ratios!F6 -> 0.15509286 | C34: =Ratios!F35 -> 0.16941215 | D34: =Ratios!F64 -> 0.058866746 | E34: =Ratios!F93 -> 0.15315507 | F34: =Ratios!F122 -> 0.026492851
A35: FY24 | B35: =Ratios!G6 -> 0.021723341 | C35: =Ratios!G35 -> -0.042118473 | D35: =Ratios!G64 -> 0.075802255 | E35: =Ratios!G93 -> 0.028709895 | F35: =Ratios!G122 -> -0.011368292
A36: FY25 | B36: =Ratios!H6 -> -0.0091766835 | C36: =Ratios!H35 -> 0.10879998 | D36: =Ratios!H64 -> 0.012818446 | E36: =Ratios!H93 -> 0.070010138 | F36: =Ratios!H122 -> 0.1220346
A37: FY26 | B37: =Ratios!I6 -> 0.051200104 | C37: =Ratios!I35 -> 0.047063978 | D37: =Ratios!I64 -> 0.050147258 | E37: =Ratios!I93 -> 0.067380037 | F37: =Ratios!I122 -> 0.25667067
A40: Cash Conversion Cycle (days)
A41: Year | B41: HUL | C41: ITC | D41: Dabur | E41: Britannia | F41: Marico
A42: FY22 | B42: =Ratios!E19 -> -64 | C42: =Ratios!E48 -> 104 | D42: =Ratios!E77 -> 13 | E42: =Ratios!E106 -> 11 | F42: =Ratios!E135 -> 30
A43: FY23 | B43: =Ratios!F19 -> -49 | C43: =Ratios!F48 -> 104 | D43: =Ratios!F77 -> 14 | E43: =Ratios!F106 -> -3 | F43: =Ratios!F135 -> 20
A44: FY24 | B44: =Ratios!G19 -> -70 | C44: =Ratios!G48 -> 148 | D44: =Ratios!G77 -> -11 | E44: =Ratios!G106 -> -9 | F44: =Ratios!G135 -> 19
A45: FY25 | B45: =Ratios!H19 -> -72 | C45: =Ratios!H48 -> 146 | D45: =Ratios!H77 -> -14 | E45: =Ratios!H106 -> -8 | F45: =Ratios!H135 -> 33
A46: FY26 | B46: =Ratios!I19 -> -89 | C46: =Ratios!I48 -> 164 | D46: =Ratios!I77 -> -26 | E46: =Ratios!I106 -> -9 | F46: =Ratios!I135 -> 12
